netmedpy/DistanceMatrix.py
netmedpy/NetMedPy.py
netmedpy/__init__.py
netmedpy-0.1.171.dist-info/licenses/LICENSE.txt
netmedpy-0.1.171.dist-info/METADATA
netmedpy-0.1.171.dist-info/WHEEL
netmedpy-0.1.171.dist-info/top_level.txt
netmedpy-0.1.171.dist-info/RECORD
