Metadata-Version: 2.4
Name: netmedpy
Version: 0.1.171
Summary: A Python package for network medicine analysis
Author: Andres Aldana, Michael Sebek, Gordana Ispirova, Rodrigo Dorantes-Gilardi, Giulia Menichetti
License: MIT License
Project-URL: Homepage, https://github.com/menicgiulia/NetMedPy
Classifier: Programming Language :: Python :: 3
Classifier: License :: OSI Approved :: MIT License
Classifier: Operating System :: OS Independent
Requires-Python: <3.12,>=3.8
License-File: LICENSE.txt
Requires-Dist: numpy
Requires-Dist: pandas
Requires-Dist: matplotlib
Requires-Dist: seaborn
Requires-Dist: scipy
Requires-Dist: networkx
Requires-Dist: ray<3.0.0,>=2.20.0
Requires-Dist: jupyter
Requires-Dist: matplotlib
Requires-Dist: ipython
Requires-Dist: seaborn
Requires-Dist: notebook
Requires-Dist: ipykernel
Dynamic: license-file
